needto/__about__.py
needto/__init__.py
needto/__main__.py
needto/src/__init__.py
needto/src/ai_client.py
needto/src/cli.py
needto/src/config.py
needto/src/utils.py
needto-0.1.9.dist-info/METADATA
needto-0.1.9.dist-info/WHEEL
needto-0.1.9.dist-info/entry_points.txt
needto-0.1.9.dist-info/licenses/LICENSE.txt
needto-0.1.9.dist-info/RECORD
