Metadata-Version: 2.4
Name: needto
Version: 0.1.9
Summary: Ask AI for help you in your terminal.
Project-URL: Documentation, https://github.com/danialkeimasi/needto#readme
Project-URL: Issues, https://github.com/danialkeimasi/needto/issues
Project-URL: Source, https://github.com/danialkeimasi/needto
Author-email: Danial Keimasi <danialkeimasi@gmail.com>
License-Expression: MIT
License-File: LICENSE.txt
Classifier: Development Status :: 4 - Beta
Classifier: Programming Language :: Python
Classifier: Programming Language :: Python :: 3.8
Classifier: Programming Language :: Python :: 3.9
Classifier: Programming Language :: Python :: 3.10
Classifier: Programming Language :: Python :: 3.11
Classifier: Programming Language :: Python :: 3.12
Classifier: Programming Language :: Python :: Implementation :: CPython
Classifier: Programming Language :: Python :: Implementation :: PyPy
Requires-Python: >=3.8
Requires-Dist: groq==0.18.0
Requires-Dist: rich==13.9.4
Requires-Dist: simple-term-menu==1.6.6
Requires-Dist: typer==0.15.1
